{
    "background-color": "#100f0b",
    "badge-color": "#bfcfde",
    "bold-color": "#bfcfde",
    "comment": "",
    "cursor-background-color": "#100f0b",
    "cursor-foreground-color": "#bfcfde",
    "foreground-color": "#bfcfde",
    "highlight-background-color": "#100f0b",
    "highlight-foreground-color": "#bfcfde",
    "name": "wal export",
    "palette": [
        "#100f0b",
        "#AC9569",
        "#737C81",
        "#789BC3",
        "#A2A5A2",
        "#BBC1BE",
        "#E3D1AF",
        "#bfcfde",
        "#85909b",
        "#AC9569",
        "#737C81",
        "#789BC3",
        "#A2A5A2",
        "#BBC1BE",
        "#E3D1AF",
        "#bfcfde"
    ],
    "use-badge-color": false,
    "use-bold-color": false,
    "use-cursor-color": false,
    "use-highlight-color": false,
    "use-theme-colors": false
}
