{
    "wallpaper": "/Users/ryuta69/Downloads/batman-sign-logo-dark-4k.jpg",
    "alpha": "100",

    "special": {
        "background": "#000000",
        "foreground": "#7ebdcf",
        "cursor": "#7ebdcf"
    },
    "colors": {
        "color0": "#000000",
        "color1": "#074E65",
        "color2": "#054A74",
        "color3": "#033886",
        "color4": "#05538A",
        "color5": "#096A94",
        "color6": "#0A74A6",
        "color7": "#7ebdcf",
        "color8": "#588490",
        "color9": "#074E65",
        "color10": "#054A74",
        "color11": "#033886",
        "color12": "#05538A",
        "color13": "#096A94",
        "color14": "#0A74A6",
        "color15": "#7ebdcf"
    }
}
